{
  "colors": {
    "bg": "#000000",
    "fg": "#E0E0E0",
    "muted": "#9aa0a6",
    "primary": "#9D00FF",
    "accent2": "#BB86FC",
    "panel": "#0d0d0d",
    "border": "#1f1f1f"
  },

  "spacing": {
    "xs": 6,
    "sm": 8,
    "md": 12,
    "lg": 16,
    "xl": 24,
    "xxl": 32,
    "xxxl": 48
  },

  "type": {
    "sm": "0.9rem",
    "base": "1rem",
    "lg": "1.125rem",
    "xl": "1.35rem",
    "xxl": "1.75rem",
    "xxxl": "2.25rem",
    "xxxxl": "3rem"
  },

  "fonts": {
    "heading": "Poppins, system-ui, -apple-system, Segoe UI, Roboto, Inter, Arial, sans-serif",
    "body": "Inter, system-ui, -apple-system, Segoe UI, Roboto, Arial, sans-serif"
  }
}
